nonebot_plugin_groups_aichat/__init__.py
nonebot_plugin_groups_aichat/config.py
nonebot_plugin_groups_aichat-0.2.0.post1.dist-info/LICENSE
nonebot_plugin_groups_aichat-0.2.0.post1.dist-info/METADATA
nonebot_plugin_groups_aichat-0.2.0.post1.dist-info/WHEEL
nonebot_plugin_groups_aichat-0.2.0.post1.dist-info/RECORD
